security_constraints/__init__.py
security_constraints/common.py
security_constraints/github_security_advisory.py
security_constraints/main.py
security_constraints/py.typed
security_constraints-1.2.1.dist-info/LICENSE
security_constraints-1.2.1.dist-info/METADATA
security_constraints-1.2.1.dist-info/WHEEL
security_constraints-1.2.1.dist-info/entry_points.txt
security_constraints-1.2.1.dist-info/top_level.txt
security_constraints-1.2.1.dist-info/RECORD
