Metadata-Version: 2.1
Name: security-constraints
Version: 1.2.1
Summary: Fetches security vulnerabilities and creates pip-constraints based on them.
Author: Anton Vikström
License: Apache License
Project-URL: repo, https://github.com/mam-dev/security-constraints
Classifier: Development Status :: 5 - Production/Stable
Classifier: Programming Language :: Python :: 3.8
Classifier: Programming Language :: Python :: 3.9
Classifier: Programming Language :: Python :: 3.10
Classifier: Programming Language :: Python :: 3.11
Classifier: Programming Language :: Python :: 3.12
Classifier: Topic :: Security
Classifier: License :: OSI Approved :: Apache Software License
Requires-Python: >=3.8
License-File: LICENSE
Requires-Dist: requests
Requires-Dist: pyyaml
